ralphx/__init__.py
ralphx/cli.py
ralphx/mcp_server.py
ralphx/adapters/__init__.py
ralphx/adapters/base.py
ralphx/adapters/claude_cli.py
ralphx/api/__init__.py
ralphx/api/main.py
ralphx/api/routes/__init__.py
ralphx/api/routes/auth.py
ralphx/api/routes/config.py
ralphx/api/routes/export_import.py
ralphx/api/routes/files.py
ralphx/api/routes/filesystem.py
ralphx/api/routes/imports.py
ralphx/api/routes/items.py
ralphx/api/routes/logs.py
ralphx/api/routes/loops.py
ralphx/api/routes/planning.py
ralphx/api/routes/projects.py
ralphx/api/routes/resources.py
ralphx/api/routes/runs.py
ralphx/api/routes/stream.py
ralphx/api/routes/templates.py
ralphx/api/routes/workflows.py
ralphx/core/__init__.py
ralphx/core/auth.py
ralphx/core/checkpoint.py
ralphx/core/database.py
ralphx/core/dependencies.py
ralphx/core/display.py
ralphx/core/doctor.py
ralphx/core/executor.py
ralphx/core/global_db.py
ralphx/core/guardrails.py
ralphx/core/import_manager.py
ralphx/core/input_templates.py
ralphx/core/logger.py
ralphx/core/loop.py
ralphx/core/loop_templates.py
ralphx/core/oauth.py
ralphx/core/permission_templates.py
ralphx/core/permissions.py
ralphx/core/planning_service.py
ralphx/core/preview.py
ralphx/core/project.py
ralphx/core/project_db.py
ralphx/core/project_export.py
ralphx/core/project_import.py
ralphx/core/resources.py
ralphx/core/sample_project.py
ralphx/core/schemas.py
ralphx/core/session.py
ralphx/core/templates.py
ralphx/core/workflow_executor.py
ralphx/core/workflow_export.py
ralphx/core/workflow_import.py
ralphx/core/workspace.py
ralphx/mcp/__init__.py
ralphx/mcp/base.py
ralphx/mcp/registry.py
ralphx/mcp/server.py
ralphx/mcp/tools/__init__.py
ralphx/mcp/tools/diagnostics.py
ralphx/mcp/tools/guardrails.py
ralphx/mcp/tools/help.py
ralphx/mcp/tools/imports.py
ralphx/mcp/tools/items.py
ralphx/mcp/tools/loops.py
ralphx/mcp/tools/monitoring.py
ralphx/mcp/tools/permissions.py
ralphx/mcp/tools/projects.py
ralphx/mcp/tools/resources.py
ralphx/mcp/tools/workflows.py
ralphx-0.3.5.dist-info/METADATA
ralphx-0.3.5.dist-info/WHEEL
ralphx-0.3.5.dist-info/entry_points.txt
ralphx-0.3.5.dist-info/RECORD
