Metadata-Version: 2.4
Name: ralphx
Version: 0.3.5
Summary: Autonomous AI loop orchestration for Claude Code - define workflows in YAML, run autonomously, monitor in real-time
Project-URL: Homepage, https://github.com/jackneil/ralphx
Project-URL: Repository, https://github.com/jackneil/ralphx
Project-URL: Documentation, https://github.com/jackneil/ralphx#readme
Author-email: Jack Neil <jack@jackmd.com>
License-Expression: MIT
Keywords: agent,ai,automation,claude,llm,orchestration,workflow
Classifier: Development Status :: 3 - Alpha
Classifier: Intended Audience :: Developers
Classifier: License :: OSI Approved :: MIT License
Classifier: Programming Language :: Python :: 3
Classifier: Programming Language :: Python :: 3.10
Classifier: Programming Language :: Python :: 3.11
Classifier: Programming Language :: Python :: 3.12
Classifier: Topic :: Software Development :: Libraries :: Python Modules
Requires-Python: >=3.10
Requires-Dist: aiofiles>=23.0
Requires-Dist: aiohttp>=3.9.0
Requires-Dist: fastapi>=0.100
Requires-Dist: httpx>=0.24
Requires-Dist: pydantic>=2.0
Requires-Dist: python-multipart>=0.0.6
Requires-Dist: pyyaml>=6.0
Requires-Dist: rich>=13.0
Requires-Dist: sse-starlette>=1.0
Requires-Dist: typer>=0.9
Requires-Dist: uvicorn[standard]>=0.20
Requires-Dist: watchfiles>=0.20
Provides-Extra: dev
Requires-Dist: httpx>=0.24; extra == 'dev'
Requires-Dist: pytest-asyncio>=0.21; extra == 'dev'
Requires-Dist: pytest>=7.0; extra == 'dev'
Requires-Dist: ruff>=0.1; extra == 'dev'
